odoo/addons/pos_order_new_line/README.rst
odoo/addons/pos_order_new_line/__init__.py
odoo/addons/pos_order_new_line/__manifest__.py
odoo/addons/pos_order_new_line/i18n/es.po
odoo/addons/pos_order_new_line/i18n/fr.po
odoo/addons/pos_order_new_line/i18n/it.po
odoo/addons/pos_order_new_line/i18n/pos_order_new_line.pot
odoo/addons/pos_order_new_line/readme/CONTRIBUTORS.rst
odoo/addons/pos_order_new_line/readme/CREDITS.rst
odoo/addons/pos_order_new_line/readme/DESCRIPTION.rst
odoo/addons/pos_order_new_line/readme/USAGE.rst
odoo/addons/pos_order_new_line/static/description/icon.png
odoo/addons/pos_order_new_line/static/description/index.html
odoo/addons/pos_order_new_line/static/description/new_line_button.png
odoo/addons/pos_order_new_line/static/src/js/NewlineButton.esm.js
odoo/addons/pos_order_new_line/static/src/js/Order.esm.js
odoo/addons/pos_order_new_line/static/src/js/OrderLine.esm.js
odoo/addons/pos_order_new_line/static/src/xml/NewlineButton.xml
odoo_addon_pos_order_new_line-16.0.1.0.0.6.dist-info/METADATA
odoo_addon_pos_order_new_line-16.0.1.0.0.6.dist-info/WHEEL
odoo_addon_pos_order_new_line-16.0.1.0.0.6.dist-info/top_level.txt
odoo_addon_pos_order_new_line-16.0.1.0.0.6.dist-info/RECORD
